parseify/__init__.py
parseify/core.py
parseify/extractors/__init__.py
parseify/extractors/dom_extractor.py
parseify/parsers/__init__.py
parseify/parsers/base_parser.py
parseify/parsers/openai_parser.py
parseify/scrapers/__init__.py
parseify/scrapers/base_scraper.py
parseify/scrapers/requests_scraper.py
parseify/scrapers/scraperapi_scraper.py
parseify/scrapers/scrapingbee_scraper.py
tests/__init__.py
tests/tests_parseify.py
parseify-0.6.dist-info/METADATA
parseify-0.6.dist-info/WHEEL
parseify-0.6.dist-info/top_level.txt
parseify-0.6.dist-info/RECORD
