Metadata-Version: 2.1
Name: parseify
Version: 0.6
Summary: Get any information from any website you need.
Author: Juan Camilo Lopez
License: MIT
Requires-Dist: requests
Requires-Dist: lxml
Requires-Dist: openai
